{
    "_id": "download_item_5d1a1f277267e13bcc69fd6287251c88",
    "type": "download_item",
    "default_language": "en",
    "languages": [
        "hr",
        "en",
        "sk",
        "ro",
        "nl",
        "bg",
        "cs",
        "da",
        "de",
        "el",
        "es",
        "et",
        "fi",
        "fr",
        "ga",
        "hu",
        "it",
        "pt",
        "mt",
        "lv",
        "pl",
        "lt",
        "sv",
        "sl"
    ],
    "fields": {
        "title": {
            "bg": [
                "ЕС в слайдове"
            ],
            "cs": [
                "Prezentace o EU"
            ],
            "da": [
                "EU i slides"
            ],
            "de": [
                "Die EU – eine Folienpräsentation"
            ],
            "el": [
                "H EE σε διαφάνειες"
            ],
            "en": [
                "The EU in slides"
            ],
            "es": [
                "La UE: diapositivas"
            ],
            "et": [
                "EL slaidides"
            ],
            "fi": [
                "EU-diaesitys"
            ],
            "fr": [
                "L'UE en diaporama"
            ],
            "ga": [
                "An AE ar shleamhnáin"
            ],
            "hr": [
                "EU u dijapozitivima"
            ],
            "hu": [
                "Az EU képekben"
            ],
            "it": [
                "L'UE: schede informative"
            ],
            "lt": [
                "Skaidrės apie ES"
            ],
            "lv": [
                "Prezentāciju materiāls par ES"
            ],
            "mt": [
                "Ritratti tal-UE"
            ],
            "nl": [
                "De EU in slides"
            ],
            "pl": [
                "UE na slajdach"
            ],
            "pt": [
                "A UE em diapositivos"
            ],
            "ro": [
                "UE în imagini"
            ],
            "sk": [
                "Prezentácia o EÚ"
            ],
            "sl": [
                "EU na diapozitivih"
            ],
            "sv": [
                "Presentationsbilder om EU"
            ]
        },
        "link": {
            "bg": [
                "http://europa.eu/publications/slide-presentations/index_bg.htm"
            ],
            "cs": [
                "http://europa.eu/publications/slide-presentations/index_cs.htm"
            ],
            "da": [
                "http://europa.eu/publications/slide-presentations/index_da.htm"
            ],
            "de": [
                "http://europa.eu/publications/slide-presentations/index_de.htm"
            ],
            "el": [
                "http://europa.eu/publications/slide-presentations/index_el.htm"
            ],
            "en": [
                "http://europa.eu/publications/slide-presentations/index_en.htm"
            ],
            "es": [
                "http://europa.eu/publications/slide-presentations/index_es.htm"
            ],
            "et": [
                "http://europa.eu/publications/slide-presentations/index_et.htm"
            ],
            "fi": [
                "http://europa.eu/publications/slide-presentations/index_fi.htm"
            ],
            "fr": [
                "http://europa.eu/publications/slide-presentations/index_fr.htm"
            ],
            "ga": [
                "http://europa.eu/publications/slide-presentations/index_ga.htm"
            ],
            "hr": [
                "http://europa.eu/publications/slide-presentations/index_hr.htm"
            ],
            "hu": [
                "http://europa.eu/publications/slide-presentations/index_hu.htm"
            ],
            "it": [
                "http://europa.eu/publications/slide-presentations/index_it.htm"
            ],
            "lt": [
                "http://europa.eu/publications/slide-presentations/index_lt.htm"
            ],
            "lv": [
                "http://europa.eu/publications/slide-presentations/index_lv.htm"
            ],
            "mt": [
                "http://europa.eu/publications/slide-presentations/index_mt.htm"
            ],
            "nl": [
                "http://europa.eu/publications/slide-presentations/index_nl.htm"
            ],
            "pl": [
                "http://europa.eu/publications/slide-presentations/index_pl.htm"
            ],
            "pt": [
                "http://europa.eu/publications/slide-presentations/index_pt.htm"
            ],
            "ro": [
                "http://europa.eu/publications/slide-presentations/index_ro.htm"
            ],
            "sk": [
                "http://europa.eu/publications/slide-presentations/index_sk.htm"
            ],
            "sl": [
                "http://europa.eu/publications/slide-presentations/index_sl.htm"
            ],
            "sv": [
                "http://europa.eu/publications/slide-presentations/index_sv.htm"
            ]
        },
        "document_title": {
            "bg": [
                "Европейският химн"
            ],
            "cs": [
                "Evropská hymna"
            ],
            "da": [
                "Europahymnen"
            ],
            "de": [
                "Die Europäische Hymne"
            ],
            "el": [
                "Ο ύμνος της ΕΕ"
            ],
            "en": [
                "The European anthem"
            ],
            "es": [
                "El himno europeo"
            ],
            "et": [
                "Euroopa hümn"
            ],
            "fi": [
                "Euroopan hymni"
            ],
            "fr": [
                "L'hymne européen"
            ],
            "ga": [
                "Aintiún na hEorpa"
            ],
            "hr": [
                "europska himna"
            ],
            "hu": [
                "Az európai himnusz"
            ],
            "it": [
                "L'inno europeo"
            ],
            "lt": [
                "Europos Sąjungos himnas"
            ],
            "lv": [
                "Eiropas himna"
            ],
            "mt": [
                "L-innu Ewropew"
            ],
            "nl": [
                "De Europese hymne"
            ],
            "pl": [
                "Hymn europejski"
            ],
            "pt": [
                "O hino europeu"
            ],
            "ro": [
                "Imnul european"
            ],
            "sk": [
                "Európska hymna"
            ],
            "sl": [
                "Evropska himna"
            ],
            "sv": [
                "Europahymnen"
            ]
        }
    }
}