{
    "_id": "9c07f09da17852aca189525f9943f171",
    "type": "menu",
    "default_language": "da",
    "languages": [
        "bg",
        "cs",
        "da",
        "de",
        "et",
        "el",
        "und",
        "es",
        "fr",
        "ga",
        "it",
        "lv",
        "lt",
        "hu",
        "mt",
        "nl",
        "pl",
        "pt",
        "ro",
        "sk",
        "sl",
        "fi",
        "sv",
        "hr"
    ],
    "fields": {
        "reference_date": {
            "und": [
                "2010-04-19 0:00:00"
            ]
        },
        "weight": {
            "und": [
                93
            ]
        },
        "parent": {
            "und": [
                "76554768a735d7a484863ef47c534d7b"
            ]
        },
        "level": {
            "und": [
                5
            ]
        },
        "title": {
            "bg": [
                1972
            ],
            "cs": [
                1972
            ],
            "da": [
                1972
            ],
            "de": [
                1972
            ],
            "el": [
                1972
            ],
            "und": [
                1972
            ],
            "es": [
                1972
            ],
            "et": [
                1972
            ],
            "fi": [
                1972
            ],
            "fr": [
                1972
            ],
            "ga": [
                1972
            ],
            "hr": [
                "1972."
            ],
            "hu": [
                1972
            ],
            "it": [
                1972
            ],
            "lt": [
                "1972 m."
            ],
            "lv": [
                1972
            ],
            "mt": [
                1972
            ],
            "nl": [
                1972
            ],
            "pl": [
                1972
            ],
            "pt": [
                1972
            ],
            "ro": [
                1972
            ],
            "sk": [
                1972
            ],
            "sl": [
                1972
            ],
            "sv": [
                1972
            ]
        },
        "link": {
            "bg": [
                "about-eu/eu-history/1970-1979/1972"
            ],
            "cs": [
                "about-eu/eu-history/1970-1979/1972"
            ],
            "da": [
                "about-eu/eu-history/1970-1979/1972"
            ],
            "de": [
                "about-eu/eu-history/1970-1979/1972"
            ],
            "el": [
                "about-eu/eu-history/1970-1979/1972"
            ],
            "und": [
                "about-eu/eu-history/1970-1979/1972"
            ],
            "es": [
                "about-eu/eu-history/1970-1979/1972"
            ],
            "et": [
                "about-eu/eu-history/1970-1979/1972"
            ],
            "fi": [
                "about-eu/eu-history/1970-1979/1972"
            ],
            "fr": [
                "about-eu/eu-history/1970-1979/1972"
            ],
            "ga": [
                "about-eu/eu-history/1970-1979/1972"
            ],
            "hr": [
                "about-eu/eu-history/1970-1979/1972"
            ],
            "hu": [
                "about-eu/eu-history/1970-1979/1972"
            ],
            "it": [
                "about-eu/eu-history/1970-1979/1972"
            ],
            "lt": [
                "about-eu/eu-history/1970-1979/1972"
            ],
            "lv": [
                "about-eu/eu-history/1970-1979/1972"
            ],
            "mt": [
                "about-eu/eu-history/1970-1979/1972"
            ],
            "nl": [
                "about-eu/eu-history/1970-1979/1972"
            ],
            "pl": [
                "about-eu/eu-history/1970-1979/1972"
            ],
            "pt": [
                "about-eu/eu-history/1970-1979/1972"
            ],
            "ro": [
                "about-eu/eu-history/1970-1979/1972"
            ],
            "sk": [
                "about-eu/eu-history/1970-1979/1972"
            ],
            "sl": [
                "about-eu/eu-history/1970-1979/1972"
            ],
            "sv": [
                "about-eu/eu-history/1970-1979/1972"
            ]
        }
    }
}