{
    "_id": "8b07b05c558f5b9933a81c0f38faedfc",
    "type": "menu",
    "default_language": "und",
    "languages": [
        "bg",
        "cs",
        "da",
        "de",
        "et",
        "el",
        "und",
        "es",
        "fr",
        "ga",
        "it",
        "lv",
        "lt",
        "hu",
        "mt",
        "nl",
        "pl",
        "pt",
        "ro",
        "sk",
        "sl",
        "fi",
        "sv",
        "hr"
    ],
    "fields": {
        "reference_date": {
            "und": [
                "2010-12-13 12:33:00"
            ]
        },
        "weight": {
            "und": [
                227
            ]
        },
        "parent": {
            "und": [
                "e0bc4fc60817bb38d3964aebcc81b81d"
            ]
        },
        "level": {
            "und": [
                4
            ]
        },
        "title": {
            "bg": [
                "Кой получава пари от ЕС?"
            ],
            "cs": [
                "Kdo je příjemcem finančních prostředků EU?"
            ],
            "da": [
                "Hvem modtager EU-støtte?"
            ],
            "de": [
                "Empfänger von EU-Finanzmitteln"
            ],
            "el": [
                "Ποιοι λαμβάνουν χρηματοδότηση της ΕΕ;"
            ],
            "und": [
                "Who receives EU money?"
            ],
            "es": [
                "¿Quién recibe fondos de la UE?"
            ],
            "et": [
                "Kes saab ELi vahendeid?"
            ],
            "fi": [
                "EU-rahoituksen ja hankintasopimusten saajat"
            ],
            "fr": [
                "Qui bénéficie des fonds européens?"
            ],
            "ga": [
                "Cé a fhaigheann airgead ón AE?"
            ],
            "hr": [
                "Tko prima novac EU?"
            ],
            "hu": [
                "Az uniós források kedvezményezettjei"
            ],
            "it": [
                "Chi riceve denaro dall'UE?"
            ],
            "lt": [
                "Kas gauna ES lėšas"
            ],
            "lv": [
                "Kas saņem ES naudu?"
            ],
            "mt": [
                "Min jingħata flus mill-UE?"
            ],
            "nl": [
                "Wie heeft er al geld van de EU gekregen?"
            ],
            "pl": [
                "Kto otrzymuje dotacje od UE?"
            ],
            "pt": [
                "Quem recebe os fundos da UE"
            ],
            "ro": [
                "Beneficiarii fondurilor UE"
            ],
            "sk": [
                "Kto získal financie z EÚ?"
            ],
            "sl": [
                "Kdo so prejemniki sredstev EU"
            ],
            "sv": [
                "Vem får EU-pengar?"
            ]
        },
        "link": {
            "bg": [
                ""
            ],
            "cs": [
                ""
            ],
            "da": [
                ""
            ],
            "de": [
                ""
            ],
            "el": [
                ""
            ],
            "und": [
                ""
            ],
            "es": [
                ""
            ],
            "et": [
                ""
            ],
            "fi": [
                ""
            ],
            "fr": [
                ""
            ],
            "ga": [
                ""
            ],
            "hr": [
                "empty"
            ],
            "hu": [
                ""
            ],
            "it": [
                ""
            ],
            "lt": [
                ""
            ],
            "lv": [
                ""
            ],
            "mt": [
                ""
            ],
            "nl": [
                ""
            ],
            "pl": [
                ""
            ],
            "pt": [
                ""
            ],
            "ro": [
                ""
            ],
            "sk": [
                ""
            ],
            "sl": [
                ""
            ],
            "sv": [
                ""
            ]
        }
    }
}