{
  "_id": "bd78a56dafdade0e9d7d824b9a5f87a4",
  "type": "common_page",
  "default_language": "en",
  "languages": [
    "en",
    "bg",
    "cs",
    "da",
    "sv",
    "de",
    "el",
    "es",
    "et",
    "fi",
    "fr",
    "ga",
    "hr",
    "hu",
    "it",
    "lt",
    "lv",
    "mt",
    "nl",
    "pl",
    "pt",
    "ro",
    "sk",
    "sl"
  ],
  "fields": {
    "original_url": {
      "bg": [
        "http://europa.eu/contact/write-to-us/index_bg.htm"
      ],
      "cs": [
        "http://europa.eu/contact/write-to-us/index_cs.htm"
      ],
      "da": [
        "http://europa.eu/contact/write-to-us/index_da.htm"
      ],
      "de": [
        "http://europa.eu/contact/write-to-us/index_de.htm"
      ],
      "el": [
        "http://europa.eu/contact/write-to-us/index_el.htm"
      ],
      "en": [
        "http://europa.eu/contact/write-to-us/index_en.htm"
      ],
      "es": [
        "http://europa.eu/contact/write-to-us/index_es.htm"
      ],
      "et": [
        "http://europa.eu/contact/write-to-us/index_et.htm"
      ],
      "fi": [
        "http://europa.eu/contact/write-to-us/index_fi.htm"
      ],
      "fr": [
        "http://europa.eu/contact/write-to-us/index_fr.htm"
      ],
      "ga": [
        "http://europa.eu/contact/write-to-us/index_ga.htm"
      ],
      "hr": [
        "http://europa.eu/contact/write-to-us/index_hr.htm"
      ],
      "hu": [
        "http://europa.eu/contact/write-to-us/index_hu.htm"
      ],
      "it": [
        "http://europa.eu/contact/write-to-us/index_it.htm"
      ],
      "lt": [
        "http://europa.eu/contact/write-to-us/index_lt.htm"
      ],
      "lv": [
        "http://europa.eu/contact/write-to-us/index_lv.htm"
      ],
      "mt": [
        "http://europa.eu/contact/write-to-us/index_mt.htm"
      ],
      "nl": [
        "http://europa.eu/contact/write-to-us/index_nl.htm"
      ],
      "pl": [
        "http://europa.eu/contact/write-to-us/index_pl.htm"
      ],
      "pt": [
        "http://europa.eu/contact/write-to-us/index_pt.htm"
      ],
      "ro": [
        "http://europa.eu/contact/write-to-us/index_ro.htm"
      ],
      "sk": [
        "http://europa.eu/contact/write-to-us/index_sk.htm"
      ],
      "sl": [
        "http://europa.eu/contact/write-to-us/index_sl.htm"
      ],
      "sv": [
        "http://europa.eu/contact/write-to-us/index_sv.htm"
      ]
    },
    "title": {
      "bg": [
        "електронна поща"
      ],
      "cs": [
        "E-mail"
      ],
      "da": [
        "E-mail"
      ],
      "de": [
        "E-Mail"
      ],
      "el": [
        "Ηλεκτρονικά μηνύματα"
      ],
      "en": [
        "E-mail"
      ],
      "es": [
        "Correo electrónico"
      ],
      "et": [
        "E-post"
      ],
      "fi": [
        "Sähköposti"
      ],
      "fr": [
        "Courrier électronique"
      ],
      "ga": [
        "Ríomhphost"
      ],
      "hr": [
        "adresa e-pošte"
      ],
      "hu": [
        "Elektronikus levélváltás"
      ],
      "it": [
        "E-mail"
      ],
      "lt": [
        "E. paštas"
      ],
      "lv": [
        "E-pasts"
      ],
      "mt": [
        "L-email"
      ],
      "nl": [
        "E-mail"
      ],
      "pl": [
        "E-mail"
      ],
      "pt": [
        "Correio eletrónico"
      ],
      "ro": [
        "E-mail"
      ],
      "sk": [
        "E-mailové otázky"
      ],
      "sl": [
        "E-sporočila"
      ],
      "sv": [
        "Mejla oss"
      ]
    },
    "meta_reference": {
      "bg": [
        "EUROPA/EUROPEDIRECT/WRITE-TO-US/ENQUIRY_FORM/EN"
      ],
      "cs": [
        "EUROPA/EUROPEDIRECT/WRITE-TO-US/ENQUIRY_FORM/EN"
      ],
      "da": [
        "EUROPA/EUROPEDIRECT/WRITE-TO-US/ENQUIRY_FORM/EN"
      ],
      "de": [
        "EUROPA/EUROPEDIRECT/WRITE-TO-US/ENQUIRY_FORM/EN"
      ],
      "el": [
        "EUROPA/EUROPEDIRECT/WRITE-TO-US/ENQUIRY_FORM/EN"
      ],
      "en": [
        "EUROPA/EUROPEDIRECT/WRITE-TO-US/ENQUIRY_FORM/EN"
      ],
      "es": [
        "EUROPA/EUROPEDIRECT/WRITE-TO-US/ENQUIRY_FORM/EN"
      ],
      "et": [
        "EUROPA/EUROPEDIRECT/WRITE-TO-US/ENQUIRY_FORM/EN"
      ],
      "fi": [
        "EUROPA/EUROPEDIRECT/WRITE-TO-US/ENQUIRY_FORM/EN"
      ],
      "fr": [
        "EUROPA/EUROPEDIRECT/WRITE-TO-US/ENQUIRY_FORM/EN"
      ],
      "ga": [
        "EUROPA/EUROPEDIRECT/WRITE-TO-US/ENQUIRY_FORM/EN"
      ],
      "hr": [
        "EUROPA/EUROPEDIRECT/WRITE-TO-US/ENQUIRY_FORM/EN"
      ],
      "hu": [
        "EUROPA/EUROPEDIRECT/WRITE-TO-US/ENQUIRY_FORM/EN"
      ],
      "it": [
        "EUROPA/EUROPEDIRECT/WRITE-TO-US/ENQUIRY_FORM/EN"
      ],
      "lt": [
        "EUROPA/EUROPEDIRECT/WRITE-TO-US/ENQUIRY_FORM/EN"
      ],
      "lv": [
        "EUROPA/EUROPEDIRECT/WRITE-TO-US/ENQUIRY_FORM/EN"
      ],
      "mt": [
        "EUROPA/EUROPEDIRECT/WRITE-TO-US/ENQUIRY_FORM/EN"
      ],
      "nl": [
        "EUROPA/EUROPEDIRECT/WRITE-TO-US/ENQUIRY_FORM/EN"
      ],
      "pl": [
        "EUROPA/EUROPEDIRECT/WRITE-TO-US/ENQUIRY_FORM/EN"
      ],
      "pt": [
        "EUROPA/EUROPEDIRECT/WRITE-TO-US/ENQUIRY_FORM/EN"
      ],
      "ro": [
        "EUROPA/EUROPEDIRECT/WRITE-TO-US/ENQUIRY_FORM/EN"
      ],
      "sk": [
        "EUROPA/EUROPEDIRECT/WRITE-TO-US/ENQUIRY_FORM/EN"
      ],
      "sl": [
        "EUROPA/EUROPEDIRECT/WRITE-TO-US/ENQUIRY_FORM/EN"
      ],
      "sv": [
        "EUROPA/EUROPEDIRECT/WRITE-TO-US/ENQUIRY_FORM/EN"
      ]
    },
    "meta_creator": {
      "bg": [
        "COMM/COMM-CO2"
      ],
      "cs": [
        "COMM/COMM-CO2"
      ],
      "da": [
        "COMM/COMM-CO2"
      ],
      "de": [
        "COMM/COMM-CO2"
      ],
      "el": [
        "COMM/COMM-CO2"
      ],
      "en": [
        "COMM/COMM-CO2"
      ],
      "es": [
        "COMM/COMM-CO2"
      ],
      "et": [
        "COMM/COMM-CO2"
      ],
      "fi": [
        "COMM/COMM-CO2"
      ],
      "fr": [
        "COMM/COMM-CO2"
      ],
      "ga": [
        "COMM/COMM-CO2"
      ],
      "hr": [
        "COMM/COMM-CO2"
      ],
      "hu": [
        "COMM/COMM-CO2"
      ],
      "it": [
        "COMM/COMM-CO2"
      ],
      "lt": [
        "COMM/COMM-CO2"
      ],
      "lv": [
        "COMM/COMM-CO2"
      ],
      "mt": [
        "COMM/COMM-CO2"
      ],
      "nl": [
        "COMM/COMM-CO2"
      ],
      "pl": [
        "COMM/COMM-CO2"
      ],
      "pt": [
        "COMM/COMM-CO2"
      ],
      "ro": [
        "COMM/COMM-CO2"
      ],
      "sk": [
        "COMM/COMM-CO2"
      ],
      "sl": [
        "COMM/COMM-CO2"
      ],
      "sv": [
        "COMM/COMM-CO2"
      ]
    },
    "meta_document_type": {
      "bg": [
        "58-Document for general distribution (intended for the general public)"
      ],
      "cs": [
        "58-Document for general distribution (intended for the general public)"
      ],
      "da": [
        "58-Document for general distribution (intended for the general public)"
      ],
      "de": [
        "58-Document for general distribution (intended for the general public)"
      ],
      "el": [
        "58-Document for general distribution (intended for the general public)"
      ],
      "en": [
        "58-Document for general distribution (intended for the general public)"
      ],
      "es": [
        "58-Document for general distribution (intended for the general public)"
      ],
      "et": [
        "58-Document for general distribution (intended for the general public)"
      ],
      "fi": [
        "58-Document for general distribution (intended for the general public)"
      ],
      "fr": [
        "58-Document for general distribution (intended for the general public)"
      ],
      "ga": [
        "58-Document for general distribution (intended for the general public)"
      ],
      "hr": [
        "58-Document for general distribution (intended for the general public)"
      ],
      "hu": [
        "58-Document for general distribution (intended for the general public)"
      ],
      "it": [
        "58-Document for general distribution (intended for the general public)"
      ],
      "lt": [
        "58-Document for general distribution (intended for the general public)"
      ],
      "lv": [
        "58-Document for general distribution (intended for the general public)"
      ],
      "mt": [
        "58-Document for general distribution (intended for the general public)"
      ],
      "nl": [
        "58-Document for general distribution (intended for the general public)"
      ],
      "pl": [
        "58-Document for general distribution (intended for the general public)"
      ],
      "pt": [
        "58-Document for general distribution (intended for the general public)"
      ],
      "ro": [
        "58-Document for general distribution (intended for the general public)"
      ],
      "sk": [
        "58-Document for general distribution (intended for the general public)"
      ],
      "sl": [
        "58-Document for general distribution (intended for the general public)"
      ],
      "sv": [
        "58-Document for general distribution (intended for the general public)"
      ]
    },
    "meta_description": {
      "bg": [
        "Използвайте този формуляр, за да изпратите въпросите си за ЕС: Какви са правата ви съгласно правото на ЕС? Как можете да се възползвате от политика, действие или финансиране на ЕС?"
      ],
      "cs": [
        "Pomocí tohoto formuláře můžete pokládat otázky týkající se EU, např: Jaká jsou vaše práva vyplývající z právních předpisů EU? Jakým způsobem můžete politiky a akce EU využít? Jak lze získat finanční prostředky EU?"
      ],
      "da": [
        "Brug formularen her til at sende dine spørgsmål om EU: Hvilke rettigheder giver EU-retten dig? Hvordan kan du nyde godt af EU's politik, aktioner eller tilskud?"
      ],
      "de": [
        "Verwenden Sie dieses Formular für Ihre Fragen zur EU: Was sind Ihre Rechte als EU-Bürger/-in? Wie können Sie von der Politik, von Aktionen oder Fördermitteln der EU profitieren?"
      ],
      "el": [
        "Χρησιμοποιήστε αυτό το δελτίο για να στείλετε τα ερωτήματά σας σχετικά με την ΕΕ: ποια είναι τα δικαιώματά σας σύμφωνα με το δίκαιο της ΕΕ; Πώς μπορείτε να ωφεληθείτε από την πολιτική, τις δράσεις ή τις χρηματοδοτήσεις της ΕΕ;"
      ],
      "en": [
        "Use this form to send your questions about the EU: what are your rights under EU law? How can you benefit from EU policy, action or funding?"
      ],
      "es": [
        "Utilice este formulario para enviar sus preguntas sobre la UE: según la legislación europea ¿cuáles son sus derechos? ¿Cómo puede beneficiarse de las políticas, la actuación o la financiación de la UE?"
      ],
      "et": [
        "Kasutage seda vormi, et esitada oma küsimused ELi kohta, nagu: millised on teie ELi õigusaktidest tulenevad õigused? Kuidas saada kasu ELi poliitikast, meetmetest või rahastamisest?"
      ],
      "fi": [
        "Tällä lomakkeella voi lähettää EU-aiheisia kysymyksiä, kuten: Miten kansalainen voi käyttää EU:n lainsäädännön mukaisia oikeuksiaan? Miten voi hyödyntää EU:n toimia tai rahoitusta?"
      ],
      "fr": [
        "Utilisez ce formulaire pour nous adresser vos questions sur l'UE: quels sont vos droits garantis par la législation européenne? Comment bénéficier de l'action de l'UE? Comment demander un financement?"
      ],
      "ga": [
        "Bain úsáid as an bhfoirm seo le do cheisteanna faoin AE a chur chugainn Cad iad do chearta faoi dhlí an AE? Conas is féidir leat tairbhiú de bheartas, gníomhaíocht nó maoiniú de chuid an AE?"
      ],
      "hr": [
        "Pitanja o EU-u pošaljite prema sljedećem uzorku: koja su vaša prava prema zakonodavstvu EU-a?  Na koji način možete imati koristi od politika, djelovanja ili financijske potpore EU-a?"
      ],
      "hu": [
        "Töltse ki ezt az elektronikus űrlapot, ha kérdése van az Európai Unióval kapcsolatban, pl meg szeretné tudni, hogy milyen jogok illetik meg Önt az EU jogszabályai alapján, illetve hogy milyen előnyei származnak az uniós szakpolitikákból, intézkedésekből és támogatásokból."
      ],
      "it": [
        "Utilizza questo modulo per inviare domande sull'UE: Quali sono i miei diritti in base alla legislazione dell'UE? Come posso beneficiare delle politiche, delle azioni o dei finanziamenti dell'UE?"
      ],
      "lt": [
        "Naudokite šią formą, jeigu turite klausimų apie ES, pavyzdžiui norite sužinoti, kokios teisės jums užtikrinamos ES teisės aktais, kuo jums gali būti naudinga ES politika, veikla arba kokį finansavimą galite gauti?"
      ],
      "lv": [
        "Izmantojiet šo veidlapu, lai uzdotu jautājumus par ES: kādas ir jūsu tiesības saskaņā ar ES likumdošanu? Kāds ir jūsu ieguvums no ES politikas vai darbības? Kā saņemt ES finansējumu?"
      ],
      "mt": [
        "Uża din il-formola biex tibgħatilna l-mistoqsijiet tiegħek dwar l-UE: x'inhuma drittijietek skont il-liġi tal-UE? Kif tista' tgawdi mill-politika, l-azzjonijiet jew il-finanzjament tal-UE?"
      ],
      "nl": [
        "Gebruik dit formulier voor vragen over de EU: Wat zijn mijn rechten volgens de EU-wetgeving? Wat kan de EU voor mij betekenen? Kom ik in aanmerking voor subsidie?"
      ],
      "pl": [
        "Formularz, za pomocą którego mogą Państwo zadać nam pytanie na temat UE, przysługujących Państwu praw oraz korzyści płynących z polityki, działań i funduszy unijnych."
      ],
      "pt": [
        "Utilize este formulário para enviar as suas perguntas sobre a UE: quais são os meus direitos ao abrigo da legislação europeia? Como posso beneficiar das políticas, ações ou financiamentos da UE?, etc."
      ],
      "ro": [
        "Utilizaţi acest formular pentru a trimite întrebări despre UE: ce drepturi aveţi în baza legislaţiei europene? cum puteţi beneficia de anumite politici, măsuri sau fonduri europene?"
      ],
      "sk": [
        "Otázky prostredníctvom tohto formulára zasielajte, ak vás zaujíma: aké sú vaše práva podľa právnych predpisov EÚ? Aký prínos má pre vás politika, činnosť alebo financovanie EÚ?"
      ],
      "sl": [
        "Obrazec za vprašanja o EU: Kakšne so moje pravice po zakonodaji EU? Kakšne koristi mi prinašajo politike in ukrepi EU ter kako lahko pridobim sredstva EU?"
      ],
      "sv": [
        "Använd det här formuläret om du vill ställa frågor om EU: vilka rättigheter har jag enligt EU-rätten? Hur söker jag EU-bidrag eller anmäler mig till ett EU-program?"
      ]
    },
    "meta_keywords": {
      "bg": [
        "Европейски съюз",
        "ЕС",
        "Europe Direct",
        "за контакти",
        "информация",
        "електронна поща",
        "електронен адрес",
        "ел. адре",
        "въпроси",
        "отговор",
        "съвет",
        "насоки",
        "граждани",
        "Европа",
        "телефонен център",
        "информационна служба",
        "гореща линия",
        "запитвания"
      ],
      "cs": [
        "Evropská unie",
        "EU",
        "Europe Direct",
        "kontakt",
        "informace",
        "e-mail",
        "schránka",
        "dotazy",
        "otázky",
        "odpověď",
        "poradenství",
        "pokyny",
        "občané",
        "Evropa",
        "Call Center",
        "kontaktní středisko",
        "poradenská linka",
        "dotazy"
      ],
      "da": [
        "Europæiske Union",
        "EU",
        "Europe Direct",
        "kontakt",
        "information",
        "E-mail",
        "mailboks",
        "spørgsmål",
        "svar",
        "rådgivning",
        "vejledning",
        "borgere",
        "Europa",
        "call center",
        "kontaktcenter",
        "hjælpelinje",
        "forespørgsler"
      ],
      "de": [
        "Europäische Union",
        "EU",
        "Europe Direct",
        "Kontakt",
        "Information",
        "E-Mail",
        "Mailbox",
        "Fragen",
        "Antwort",
        "Beratung",
        "Rat",
        "Bürgerinnen und Bürger",
        "Europa",
        "Call-Center",
        "Callcenter",
        "Kontaktzentrum",
        "Hotline",
        "Beratung",
        "Anfragen",
        "Fragen"
      ],
      "el": [
        "Ευρωπαϊκή Ένωση",
        "ΕΕ",
        "Europe Direct",
        "επικοινωνία",
        "πληροφορίες",
        "ηλεκτρονικό μήνυμα",
        "ταχυδρομική θυρίδα",
        "ερωτήσεις",
        "απάντηση",
        "συμβουλές",
        "καθοδήγηση",
        "πολίτες",
        "Ευρώπη",
        "Τηλεφωνικό κέντρο",
        "Κέντρο επικοινωνίας",
        "γραμμή παροχής βοήθειας",
        "ερωτήματα"
      ],
      "en": [
        "European Union",
        "EU",
        "Europe Direct",
        "contact",
        "information",
        "e-mail",
        "mailbox",
        "questions",
        "answer",
        "advice",
        "guidance",
        "citizens",
        "Europe",
        "Call center",
        "Contact center",
        "helpline",
        "enquiries"
      ],
      "es": [
        "Unión Europea",
        "UE",
        "Europe Direct",
        "contacto",
        "información",
        "Correo electrónico",
        "buzón",
        "preguntas",
        "respuesta",
        "asesoramiento",
        "orientación",
        "ciudadanos",
        "Europa",
        "Atención telefónica",
        "centro de contacto",
        "líneas de ayuda",
        "preguntas"
      ],
      "et": [
        "Euroopa Liit",
        "EL",
        "Europe Direct",
        "kontakt",
        "teave",
        "e-posti aadress",
        "postkast",
        "küsimused",
        "vastus",
        "nõuanne",
        "juhendamine",
        "suunised",
        "kodanikud",
        "Euroopa",
        "kõnekeskus",
        "kontaktpunkt",
        "infoliin",
        "päringud"
      ],
      "fi": [
        "Euroopan unioni",
        "EU",
        "Europe Direct",
        "yhteydenotto",
        "tietoja",
        "sähköposti",
        "sähköpostiosoite",
        "kysymykset",
        "vastaus",
        "neuvonta",
        "opastus",
        "kansalaiset",
        "Eurooppa",
        "puhelinpalvelukeskus",
        "tietopalvelu",
        "puhelinpalvelu",
        "tiedustelut"
      ],
      "fr": [
        "Union européenne",
        "UE",
        "Europe Direct",
        "contact",
        "Information",
        "courrier électronique",
        "courriel",
        "e-mail",
        "adresse électronique",
        "boîte aux lettres",
        "messa",
        "questions",
        "Répondre",
        "réponse",
        "conseil",
        "orientation",
        "citoyens",
        "Europe",
        "Centre d'appel",
        "Centre de contact",
        "service d’assistance",
        "renseignements",
        "demandes d'informations",
        "questio"
      ],
      "ga": [
        "Aontas Eorpach",
        "AE",
        "Europe Direct",
        "teagmháil",
        "faisnéis",
        "ríomhphost",
        "bosca poist",
        "ceisteanna",
        "freagra",
        "comhairle",
        "treoir",
        "saoránaigh",
        "Eoraip",
        "Ionad glaonna",
        "Ionad teagmhála",
        "líne cabhrach",
        "fiosrúcháin"
      ],
      "hr": [
        "Europska unija",
        "EU",
        "Europe Direct",
        "kontakt",
        "informacije",
        "adresa e-pošte",
        "poštanski sandučić",
        "pitanja",
        "odgovor",
        "savjet",
        "smjernice",
        "građani",
        "Europa",
        "Pozivni centar",
        "Kontaktni centar",
        "služba za pomoć",
        "upiti"
      ],
      "hu": [
        "Európai Unió",
        "eu",
        "Europe Direct.",
        "kapcsolat",
        "információ",
        "tájékoztatás",
        "E-mail",
        "cím",
        "elektronikus levélváltás",
        "postafiók",
        "kérdések",
        "válasz",
        "tanács",
        "tanácsadás",
        "útmutatás",
        "eligazítás",
        "polgárok",
        "Európa",
        "Hívóközpont",
        "call center",
        "tájékoztató központ",
        "ügyfélszolgálati kö",
        "Segélyvonal",
        "vizsgálatok",
        "kérdések"
      ],
      "it": [
        "Unione europea",
        "UE",
        "Europe Direct",
        "contatti",
        "informazioni",
        "e-mail",
        "casella di posta elettronica",
        "mailbox",
        "domande",
        "risposta",
        "consulenza",
        "orientamento",
        "cittadini",
        "Europa",
        "numero verde",
        "sportello",
        "assistenza telefonica",
        "richieste di informazioni"
      ],
      "lt": [
        "Europos Sąjunga",
        "ES",
        "Europe Direct",
        "kontaktai",
        "informacija",
        "e. paštas",
        "paštas",
        "klausimai",
        "atsakymas",
        "patarimas",
        "konsultacija",
        "rekomendacijos",
        "piliečiai",
        "Europa",
        "Informacinių paslaugų centras",
        "Kontaktinis centras",
        "pagalbos tarnyba",
        "užklausos"
      ],
      "lv": [
        "Eiropas Savienība",
        "ES",
        "Europe Direct",
        "kontakti",
        "sazināties",
        "informācija",
        "e-pasts",
        "e-pasta adrese",
        "jautājumi",
        "atbilde",
        "konsultācijas",
        "padoms",
        "norādījumi",
        "iedzīvotāji",
        "pilsoņi",
        "Eiropa",
        "informācijas zvanu centrs",
        "kontaktpunkts",
        "palīdzības tālrunis",
        "informācijas pieprasījumi"
      ],
      "mt": [
        "Unjoni Ewropea",
        "UE",
        "Europe Direct",
        "ikkuntattja",
        "informazzjoni",
        "email",
        "kaxxa elettronika",
        "mistoqsijiet",
        "tweġiba",
        "parir",
        "gwida",
        "ċittadini",
        "Ewropa",
        "Call center",
        "Ċentru ta' kuntatt",
        "ħelplajn",
        "mistoqsijiet"
      ],
      "nl": [
        "Europese Unie",
        "EU",
        "Europe Direct",
        "contact",
        "informatie",
        "e-mail",
        "e-mailadres",
        "vragen",
        "antwoord",
        "advies",
        "hulp",
        "burgers",
        "Europa",
        "telefonisch informatiecentrum",
        "call-center",
        "contactcentrum",
        "hulplijn",
        "helpdesk",
        "informatieverzoek"
      ],
      "pl": [
        "Unia Europejska",
        "UE",
        "Europe Direct",
        "kontakt",
        "informacje",
        "e-mail",
        "skrzynka pocztowa",
        "pytania",
        "odpowiedź",
        "porada",
        "rada",
        "poradnictwo",
        "wskazówki",
        "obywatele",
        "Europa",
        "call center",
        "punkt kontaktowy",
        "infolinia",
        "pytania"
      ],
      "pt": [
        "união europeia",
        "ue",
        "europe direct",
        "contacto",
        "informações",
        "correio eletrónico",
        "endereço eletrónico",
        "caixa de correio",
        "perguntas",
        "resposta",
        "respostas",
        "aconselhamento",
        "conselhos",
        "orientação",
        "cidadãos",
        "europa",
        "central telefónica",
        "centro de atendimento",
        "serviço de assistência telefónica",
        "pedidos de informação"
      ],
      "ro": [
        "Uniunea Europeană",
        "UE",
        "Europe Direct",
        "contact",
        "informaţie",
        "prin e-mail",
        "adresă de e-mail",
        "întrebări",
        "răspuns",
        "consiliere",
        "orientare",
        "cetăţeni",
        "Europa",
        "call center",
        "punct de contact",
        "serviciu de asistenţă telefonică",
        "solicitări de informaţii"
      ],
      "sk": [
        "Európska únia",
        "EÚ",
        "Europe Direct",
        "kontakt",
        "informácie",
        "e-mail",
        "e-mailová schránka",
        "otázky",
        "odpoveď",
        "rada",
        "usmernenie",
        "občania",
        "Európa",
        "call centrum",
        "telefonické centrum",
        "telefonická",
        "Kontaktné centrum",
        "telefonická linka pomoci",
        "otázky"
      ],
      "sl": [
        "Evropska unija",
        "EU",
        "Europe Direct",
        "kontakt",
        "o zdravstvenem stanju",
        "e-naslov",
        "poštni predal",
        "vprašanja",
        "answer",
        "nasveti",
        "navodila",
        "državljani",
        "Evropa",
        "Klicni center",
        "Kontaktni center",
        "služba za pomoč",
        "poizvedbe"
      ],
      "sv": [
        "Europeiska unionen",
        "EU",
        "Europa direkt",
        "kontakt",
        "information",
        "e-post",
        "mejl",
        "e-brevlåda",
        "mejlbox",
        "frågor",
        "svar",
        "råd",
        "rådgivning",
        "vägledning",
        "allmänheten",
        "medborgare",
        "Europa",
        "call center",
        "telefontjänst",
        "informationscentrum",
        "telefonsupport",
        "förfrågningar"
      ]
    },
    "meta_classification": {
      "bg": [
        "04-000-Information Society, Communication, Information, Audiovisual, Telecommunications, Public Opinion"
      ],
      "cs": [
        "04-000-Information Society, Communication, Information, Audiovisual, Telecommunications, Public Opinion"
      ],
      "da": [
        "04-000-Information Society, Communication, Information, Audiovisual, Telecommunications, Public Opinion"
      ],
      "de": [
        "04-000-Information Society, Communication, Information, Audiovisual, Telecommunications, Public Opinion"
      ],
      "el": [
        "04-000-Information Society, Communication, Information, Audiovisual, Telecommunications, Public Opinion"
      ],
      "en": [
        "04-000-Information Society, Communication, Information, Audiovisual, Telecommunications, Public Opinion"
      ],
      "es": [
        "04-000-Information Society, Communication, Information, Audiovisual, Telecommunications, Public Opinion"
      ],
      "et": [
        "04-000-Information Society, Communication, Information, Audiovisual, Telecommunications, Public Opinion"
      ],
      "fi": [
        "04-000-Information Society, Communication, Information, Audiovisual, Telecommunications, Public Opinion"
      ],
      "fr": [
        "04-000-Information Society, Communication, Information, Audiovisual, Telecommunications, Public Opinion"
      ],
      "ga": [
        "04-000-Information Society, Communication, Information, Audiovisual, Telecommunications, Public Opinion"
      ],
      "hr": [
        "04-000-Information Society, Communication, Information, Audiovisual, Telecommunications, Public Opinion"
      ],
      "hu": [
        "04-000-Information Society, Communication, Information, Audiovisual, Telecommunications, Public Opinion"
      ],
      "it": [
        "04-000-Information Society, Communication, Information, Audiovisual, Telecommunications, Public Opinion"
      ],
      "lt": [
        "04-000-Information Society, Communication, Information, Audiovisual, Telecommunications, Public Opinion"
      ],
      "lv": [
        "04-000-Information Society, Communication, Information, Audiovisual, Telecommunications, Public Opinion"
      ],
      "mt": [
        "04-000-Information Society, Communication, Information, Audiovisual, Telecommunications, Public Opinion"
      ],
      "nl": [
        "04-000-Information Society, Communication, Information, Audiovisual, Telecommunications, Public Opinion"
      ],
      "pl": [
        "04-000-Information Society, Communication, Information, Audiovisual, Telecommunications, Public Opinion"
      ],
      "pt": [
        "04-000-Information Society, Communication, Information, Audiovisual, Telecommunications, Public Opinion"
      ],
      "ro": [
        "04-000-Information Society, Communication, Information, Audiovisual, Telecommunications, Public Opinion"
      ],
      "sk": [
        "04-000-Information Society, Communication, Information, Audiovisual, Telecommunications, Public Opinion"
      ],
      "sl": [
        "04-000-Information Society, Communication, Information, Audiovisual, Telecommunications, Public Opinion"
      ],
      "sv": [
        "04-000-Information Society, Communication, Information, Audiovisual, Telecommunications, Public Opinion"
      ]
    },
    "body": {
      "bg": [
        "<p>Напишете вашия въпрос по-долу – на който и да е от <a href=\"http://europa.eu/about-eu/facts-figures/administration/index_bg.htm#goto_2\">официалните езици на ЕС</a>. Моля, пишете колкото е възможно по-подробно и се уверете, че сте дали верни данни за връзка.</p>             <p>Обикновено ще получите <strong>отговор до 3 работни дни</strong> (за по-сложните въпроси може да е необходимо повече време).</p>             <p>                <iframe frameborder=\"0\" height=\"1020\" name=\"contacts_frame\" scrolling=\"no\"                        src=\"https://forms.communi-k.eu/livewebtools/WebForms/Standard/Standard.php?bg\"                        title=\"Mailbox\"                        width=\"90%\"/>             </p>             <p>                <strong>Отказ от отговорност</strong>             </p>             <p>Тази услуга се предоставя от Europe Direct.  Информацията, предоставяна от Europe Direct, не е правно обвързваща независимо от начина, по който се свързвате с нас.</p>"
      ],
      "cs": [
        "<p>Svůj dotaz můžete zadat níže – a to v kterémkoli z <a href=\"http://europa.eu/about-eu/facts-figures/administration/index_cs.htm#goto_2\">úředních jazyků EU</a>. Snažte se ho formulovat co nejkonkrétněji a nezapomeňte si před odesláním zkontrolovat své kontaktní údaje.</p>             <p>Odpověď zpravidla obdržíte <strong>do 3 pracovních dnů</strong> (odpověď na složitější dotazy si může vyžádat více času).</p>             <p>                <iframe frameborder=\"0\" height=\"1020\" name=\"contacts_frame\" scrolling=\"no\"                        src=\"https://forms.communi-k.eu/livewebtools/WebForms/Standard/Standard.php?cs\"                        title=\"Mailbox\"                        width=\"90%\"/>             </p>             <p>                <strong>Prohlášení o vyloučení odpovědnosti</strong>             </p>             <p>Tuto službu poskytuje Europe Direct.  Informace poskytované službou Europe Direct nejsou právně závazné, a to bez ohledu na to, jakým způsobem nás kontaktujete.</p>"
      ],
      "da": [
        "<p>Skriv dit spørgsmål nedenfor – på et hvilket som helst <a href=\"http://europa.eu/about-eu/facts-figures/administration/index_da.htm#goto_2\">officielt EU-sprog</a>. Vær så detaljeret som muligt og sørg for, at dine kontaktoplysninger er korrekte.</p>             <p>Normalt får du et <strong>svar i løbet af 3 arbejdsdage</strong> (mere komplekse spørgsmål kan tage længere).</p>             <p>                <iframe frameborder=\"0\" height=\"1020\" name=\"contacts_frame\" scrolling=\"no\"                        src=\"https://forms.communi-k.eu/livewebtools/WebForms/Standard/Standard.php?da\"                        title=\"Mailbox\"                        width=\"90%\"/>             </p>             <p>                <strong>Ansvarsfraskrivelse</strong>             </p>             <p>Denne tjeneste varetages af Europe Direct.  De oplysninger, du får fra Europe Direct, er ikke juridisk bindende, uanset hvilken måde du kontakter os på.</p>"
      ],
      "de": [
        "<p>Geben Sie Ihre Frage unten in einer der <a href=\"http://europa.eu/about-eu/facts-figures/administration/index_de.htm#goto_2\">EU-Amtssprachen</a> ein. Bitte formulieren Sie Ihre Frage so genau wie möglich und vergewissern Sie sich, dass Sie Ihre Kontaktdaten korrekt angeben.</p>             <p>In der Regel erhalten Sie <strong>innerhalb von drei Werktagen eine Antwort</strong> (bei komplexeren Fragen kann es länger dauern).</p>             <p>                <iframe frameborder=\"0\" height=\"1020\" name=\"contacts_frame\" scrolling=\"no\"                        src=\"https://forms.communi-k.eu/livewebtools/WebForms/Standard/Standard.php?de\"                        title=\"Mailbox\"                        width=\"90%\"/>             </p>             <p>                <strong>Haftungsausschluss</strong>             </p>             <p>Dieser Dienst wird von Europe Direct angeboten.  Die von Europe Direct bereitgestellten Informationen sind nicht rechtsverbindlich, ungeachtet der Art der Kontaktaufnahme. </p>"
      ],
      "el": [
        "<p>Γράψτε το ερώτημά σας παρακάτω – σε οποιαδήποτε <a href=\"http://europa.eu/about-eu/facts-figures/administration/index_el.htm#goto_2\">επίσημη γλώσσα της ΕΕ</a>. Δώστε όσο το δυνατό περισσότερες πληροφορίες και βεβαιωθείτε ότι συμπεριλάβατε τα σωστά στοιχεία επικοινωνίας σας.</p>             <p>Συνήθως, λαμβάνετε <strong>απάντηση μέσα σε 3 εργάσιμες ημέρες</strong> (για περίπλοκα ερωτήματα ενδέχεται να χρειαστεί περισσότερος χρόνος).</p>             <p>                <iframe frameborder=\"0\" height=\"1020\" name=\"contacts_frame\" scrolling=\"no\"                        src=\"https://forms.communi-k.eu/livewebtools/WebForms/Standard/Standard.php?el\"                        title=\"Mailbox\"                        width=\"90%\"/>             </p>             <p>                <strong>Αποποίηση ευθύνης</strong>             </p>             <p>Την υπηρεσία αυτή παρέχει το Europe Direct.  Οι πληροφορίες που σας παρέχει το \"Europe Direct\" δεν είναι νομικά δεσμευτικές, ανεξαρτήτως τρόπου επικοινωνίας.</p>"
      ],
      "en": [
        "<p>Type your enquiry below – in any <a href=\"http://europa.eu/about-eu/facts-figures/administration/index_en.htm#goto_2\">official EU language</a>. Please be as detailed as possible and be sure to include your correct contact details.</p>             <p>You will usually receive an <strong>answer within 3 working days</strong> (more complex enquiries may take longer).</p>             <p>                <iframe frameborder=\"0\" height=\"1020\" name=\"contacts_frame\" scrolling=\"no\"                        src=\"https://forms.communi-k.eu/livewebtools/WebForms/Standard/Standard.php?en\"                        title=\"Mailbox\"                        width=\"90%\"/>             </p>             <p>                <strong>Disclaimer</strong>             </p>             <p>This service is provided by Europe Direct.  The information delivered by Europe Direct is not legally binding, regardless  of how you contact us.</p>"
      ],
      "es": [
        "<p>Escriba su pregunta en cualquier <a href=\"http://europa.eu/about-eu/facts-figures/administration/index_es.htm#goto_2\">lengua oficial de la UE</a>. Sea lo más preciso posible e indique correctamente sus datos de contacto.</p>             <p>Por lo general, recibirá la <strong>respuesta en 3 días hábiles</strong> (las preguntas más complejas pueden llevar más tiempo).</p>             <p>                <iframe frameborder=\"0\" height=\"1020\" name=\"contacts_frame\" scrolling=\"no\"                        src=\"https://forms.communi-k.eu/livewebtools/WebForms/Standard/Standard.php?es\"                        title=\"Mailbox\"                        width=\"90%\"/>             </p>             <p>                <strong>Cláusula de exención de responsabilidad</strong>             </p>             <p>Este servicio es prestado por Europe Direct.  La información facilitada por Europe Direct no es jurídicamente vinculante, con independencia de cómo se haya puesto en contacto con nosotros.</p>"
      ],
      "et": [
        "<p>Sisestage oma päring allpool ELi mis tahes <a href=\"http://europa.eu/about-eu/facts-figures/administration/index_et.htm#goto_2\">ametlikus keeles</a>. Olge võimalikult üksikasjalik ning lisage oma täpsed kontaktandmed.</p>             <p>Üldjuhul vastame <strong>kolme tööpäeva jooksul</strong> (keerukamad päringud võivad olla aeganõudvamad).</p>             <p>                <iframe frameborder=\"0\" height=\"1020\" name=\"contacts_frame\" scrolling=\"no\"                        src=\"https://forms.communi-k.eu/livewebtools/WebForms/Standard/Standard.php?et\"                        title=\"Mailbox\"                        width=\"90%\"/>             </p>             <p>                <strong>Vastutuse välistamine</strong>             </p>             <p>Teenust osutab Europe Direct.  Europe Directi esitatav teave ei ole õiguslikult siduv, olenemata sellest, mil viisil Te meiega ühendust võtate. </p>"
      ],
      "fi": [
        "<p>Kirjoita kysymyksesi seuraavaan lomakkeeseen millä tahansa <a href=\"http://europa.eu/about-eu/facts-figures/administration/index_fi.htm#goto_2\">EU:n virallisella kielellä</a>. Anna kysymyksessäsi mahdollisimman tarkat tiedot ja muista täyttää yhteystietosi huolella.</p>             <p>Tavallisesti lähetämme <strong>vastauksen kolmen arkipäivän kuluessa</strong> (vaikeampien kysymysten selvittäminen voi kestää kauemmin).</p>             <p>                <iframe frameborder=\"0\" height=\"1020\" name=\"contacts_frame\" scrolling=\"no\"                        src=\"https://forms.communi-k.eu/livewebtools/WebForms/Standard/Standard.php?fi\"                        title=\"Mailbox\"                        width=\"90%\"/>             </p>             <p>                <strong>Vastuuvapauslauseke</strong>             </p>             <p>Tämän palvelun tarjoaja on Europe Direct.  Sen antamat tiedot eivät ole oikeudellisesti sitovia, olipa yhteydenottotapa mikä tahansa.</p>"
      ],
      "fr": [
        "<p>Saisissez votre question ci-dessous – dans n'importe quelle <a href=\"http://europa.eu/about-eu/facts-figures/administration/index_fr.htm#goto_2\">langue officielle de l'Union européenne</a>. Votre question doit être la plus détaillée possible. N'oubliez pas d'indiquer vos coordonnées exactes.</p>             <p>Vous devriez recevoir une <strong>réponse dans les 3 jours ouvrables</strong> (les questions plus complexes peuvent requérir plus de temps).</p>             <p>                <iframe frameborder=\"0\" height=\"1020\" name=\"contacts_frame\" scrolling=\"no\"                        src=\"https://forms.communi-k.eu/livewebtools/WebForms/Standard/Standard.php?fr\"                        title=\"Mailbox\"                        width=\"90%\"/>             </p>             <p>                <strong>Clause de non-responsabilité</strong>             </p>             <p>Ce service est fourni par Europe Direct.  Les informations fournies par Europe Direct ne sont pas juridiquement contraignantes, quelle que soit la manière dont vous nous contactez.</p>"
      ],
      "ga": [
        "<p>Clóscriobh d'fhiosrúchán thíos – i <a href=\"http://europa.eu/about-eu/facts-figures/administration/index_ga.htm#goto_2\">dteanga oifigiúil ar bith de chuid an AE</a>. Tabhair an méid mionsonraí agus is féidir agus cinntigh go bhfuil do shonraí teagmhála cearta san áireamh.</p>             <p>Gheobhaidh tú <strong>freagra laistigh de 3 lá oibre</strong> de ghnáth (d'fhéadfadh níos mó ama a bheith i gceist i gcás fiosrúcháin níos casta).</p>             <p>                <iframe frameborder=\"0\" height=\"1020\" name=\"contacts_frame\" scrolling=\"no\"                        src=\"https://forms.communi-k.eu/livewebtools/WebForms/Standard/Standard.php?ga\"                        title=\"Mailbox\"                        width=\"90%\"/>             </p>             <p>                <strong>Séanadh</strong>             </p>             <p>Is é Europe Direct a chuireann an tseirbhís seo ar fáil.  Níl an fhaisnéis a thugann Europe Direct ceangailteach ó thaobh dlí, beag beann ar conas a dhéanann tú teagmháil linn.</p>"
      ],
      "hr": [
        "<p>Svoj upit unesite u nastavku na jednom od <a href=\"http://europa.eu/about-eu/facts-figures/administration/index_hr.htm#goto_2\">službenih jezika EU-a</a>. Navedite sve potankosti i pripazite da su navedeni kontaktni podaci točni.</p>             <p>                <strong>Odgovor</strong> ćete vjerojatno dobiti <strong>u roku od 3 radna dana</strong> (za složenija će pitanja možda trebati više vremena).</p>             <p>                <iframe frameborder=\"0\" height=\"1020\" name=\"contacts_frame\" scrolling=\"no\"                        src=\"https://forms.communi-k.eu/livewebtools/WebForms/Standard/Standard.php?hr\"                        title=\"Mailbox\"                        width=\"90%\"/>             </p>             <p>                <strong>Izjava o ograničenju odgovornosti</strong>             </p>             <p>Ovu uslugu pruža služba Europe Direct.  Informacije dobivene od službe Europe Direct nisu pravno obvezujuće, neovisno o načinu na koji nam se obraćate.</p>"
      ],
      "hu": [
        "<p>Gépelje be kérdését az alábbi mezőbe az <a href=\"http://europa.eu/about-eu/facts-figures/administration/index_hu.htm#goto_2\">EU bármelyik hivatalos nyelvén</a>. Kérjük, kérdését részletesen fogalmazza meg és kapcsolattartási adatait pontosan adja meg.</p>             <p>Kérdésére általában <strong>3 munkanapon belül válaszolunk</strong> (a bonyolultabb kérdések feldolgozása viszont több időt vesz igénybe).</p>             <p>                <iframe frameborder=\"0\" height=\"1020\" name=\"contacts_frame\" scrolling=\"no\"                        src=\"https://forms.communi-k.eu/livewebtools/WebForms/Standard/Standard.php?hu\"                        title=\"Mailbox\"                        width=\"90%\"/>             </p>             <p>                <strong>Jogi nyilatkozat</strong>             </p>             <p>A szolgáltatás nyújtásáért a Europe Direct központ felel.  A Europe Direct által megadott információk – a kapcsolatfelvétel módjától függetlenül – nem minősülnek jogilag kötelező erejű tájékoztatásnak.</p>"
      ],
      "it": [
        "<p>Inserisci la tua richiesta di informazioni qui sotto – in qualsiasi <a href=\"http://europa.eu/about-eu/facts-figures/administration/index_it.htm#goto_2\">lingua ufficiale dell'UE</a>. Cerca di essere il più preciso possibile e accertati di aver inserito correttamente i tuoi recapiti.</p>             <p>Dovresti ricevere una <strong>risposta entro 3 giorni lavorativi</strong> (richieste complesse potrebbero richiedere più tempo).</p>             <p>                <iframe frameborder=\"0\" height=\"1020\" name=\"contacts_frame\" scrolling=\"no\"                        src=\"https://forms.communi-k.eu/livewebtools/WebForms/Standard/Standard.php?it\"                        title=\"Mailbox\"                        width=\"90%\"/>             </p>             <p>                <strong>Clausola di esclusione della responsabilità</strong>             </p>             <p>Questo servizio è fornito da Europe Direct.  Le informazioni date non sono giuridicamente vincolanti, indipendentemente da come Europe Direct viene contattato.</p>"
      ],
      "lt": [
        "<p>Toliau įrašykite savo užklausą bet kuria <a href=\"http://europa.eu/about-eu/facts-figures/administration/index_lt.htm#goto_2\">oficialiąja ES kalba</a>. Rašykite kuo išsamiau ir nurodykite tikslius savo kontaktinius duomenis.</p>             <p>Paprastai <strong>atsakymas gaunamas per 3 darbo dienas</strong> (jei atvejis sudėtingas, tai gali užtrukti ilgiau).</p>             <p>                <iframe frameborder=\"0\" height=\"1020\" name=\"contacts_frame\" scrolling=\"no\"                        src=\"https://forms.communi-k.eu/livewebtools/WebForms/Standard/Standard.php?lt\"                        title=\"Mailbox\"                        width=\"90%\"/>             </p>             <p>                <strong>Atsakomybės apribojimas</strong>             </p>             <p>Šią paslaugą teikia „Europe Direct“.  Tarnybos „Europe Direct“ pateikta informacija nėra teisiškai įpareigojanti, neatsižvelgiant į tai, kokiais būdais su mumis susisiekėte.</p>"
      ],
      "lv": [
        "<p>Aizpildiet zemāk savu informācijas pieprasījumu jebkurā <a href=\"http://europa.eu/about-eu/facts-figures/administration/index_lv.htm#goto_2\">ES oficiālajā valodā</a>. Pēc iespējas precīzāk aprakstiet, ko gribat uzzināt, un pārliecinieties, vai kontaktinformācija ir norādīta pareizi.</p>             <p>Atbildi parasti saņemsit <strong>3 darbdienu laikā</strong> (sarežģītākiem informācijas pieprasījumiem šis termiņš var būt ilgāks).</p>             <p>                <iframe frameborder=\"0\" height=\"1020\" name=\"contacts_frame\" scrolling=\"no\"                        src=\"https://forms.communi-k.eu/livewebtools/WebForms/Standard/Standard.php?lv\"                        title=\"Mailbox\"                        width=\"90%\"/>             </p>             <p>                <strong>Atruna</strong>             </p>             <p>Šo pakalpojumu sniedz “Europe Direct”.  Šā dienesta sniegtā informācija nav juridiski saistoša (neatkarīgi no tā, kādā veidā esat ar mums sazinājies).</p>"
      ],
      "mt": [
        "<p>Ittajpja l-mistoqsija tiegħek hawn taħt – bi kwalunkwe <a href=\"http://europa.eu/about-eu/facts-figures/administration/index_mt.htm#goto_2\">lingwa uffiċjali tal-UE</a>. Jekk jogħġbok kun preċiż kemm jista' jkun possibbli u kun żur li tinkludi d-dettalji ta' kuntatt korretti tiegħek.</p>             <p>Normalment għandek tirċievi <strong>tweġiba fi żmien 3 ġranet tax-xogħol</strong> (mistoqsijiet aktar kumplessi jistgħu jieħdu aktar fit-tul).</p>             <p>                <iframe frameborder=\"0\" height=\"1020\" name=\"contacts_frame\" scrolling=\"no\"                        src=\"https://forms.communi-k.eu/livewebtools/WebForms/Standard/Standard.php?mt\"                        title=\"Mailbox\"                        width=\"90%\"/>             </p>             <p>                <strong>Dikjarazzjoni ta’ rinunzja</strong>             </p>             <p>Dan is-servizz hu pprovdut minn Europe Direct.  L-informazzjoni mogħtija minn Europe Direct ma torbotx legalment, irrispettivament minn kif tikkuntattjana.</p>"
      ],
      "nl": [
        "<p>Stel uw vraag hieronder in een van de <a href=\"http://europa.eu/about-eu/facts-figures/administration/index_nl.htm#goto_2\">officiële EU-talen</a>. Wees zo duidelijk mogelijk en zorg ervoor dat uw contactgegevens kloppen.</p>             <p>U krijgt meestal <strong>binnen drie werkdagen</strong> antwoord (als uw vraag tenminste niet te ingewikkeld is).</p>             <p>                <iframe frameborder=\"0\" height=\"1020\" name=\"contacts_frame\" scrolling=\"no\"                        src=\"https://forms.communi-k.eu/livewebtools/WebForms/Standard/Standard.php?nl\"                        title=\"Mailbox\"                        width=\"90%\"/>             </p>             <p>                <strong>Disclaimer</strong>             </p>             <p>Dit is een service van Europe Direct.  De door Europe Direct verstrekte informatie is niet juridisch bindend, ongeacht de wijze waarop u contact heeft opgenomen.</p>"
      ],
      "pl": [
        "<p>Zapytanie można wpisać poniżej w dowolnym <a href=\"http://europa.eu/about-eu/facts-figures/administration/index_pl.htm#goto_2\">języku urzędowym UE</a>. Prosimy podać jak najwięcej szczegółów i sprawdzić, czy podali Państwo prawidłowe dane kontaktowe.</p>             <p>Z reguły <strong>odpowiedź otrzymają Państwo w ciągu 3 dni roboczych</strong> (jeśli pytanie jest bardziej skomplikowane, może to potrwać dłużej).</p>             <p>                <iframe frameborder=\"0\" height=\"1020\" name=\"contacts_frame\" scrolling=\"no\"                        src=\"https://forms.communi-k.eu/livewebtools/WebForms/Standard/Standard.php?pl\"                        title=\"Mailbox\"                        width=\"90%\"/>             </p>             <p>                <strong>Klauzula o wyłączeniu odpowiedzialności</strong>             </p>             <p>Usługę tę świadczy Europe Direct.  Informacje udzielone przez Europe Direct nie są prawnie wiążące, niezależnie od tego, w jaki sposób się Państwo z nami skontaktowali.</p>"
      ],
      "pt": [
        "<p>Insira o seu pedido de informação no formulário <i>infra</i> (em qualquer <a href=\"http://europa.eu/about-eu/facts-figures/administration/index_pt.htm#goto_2\">língua oficial da UE</a>). Procure ser o mais conciso possível e certifique-se de que os seus dados de contacto estão corretos.</p>             <p>Deverá receber uma <strong>resposta dentro de 3 dias úteis</strong> (as respostas a pedidos mais complexos poderão demorar mais tempo).</p>             <p>                <iframe frameborder=\"0\" height=\"1020\" name=\"contacts_frame\" scrolling=\"no\"                        src=\"https://forms.communi-k.eu/livewebtools/WebForms/Standard/Standard.php?pt\"                        title=\"Mailbox\"                        width=\"90%\"/>             </p>             <p>                <strong>Declaração de exoneração de responsabilidade</strong>             </p>             <p>Este serviço é prestado pelo Europe Direct.  As informações dadas não são juridicamente vinculativas, independentemente da forma como o Europe Direct é contactado.</p>"
      ],
      "ro": [
        "<p>Introduceţi cererea de informaţii mai jos, în orice <a href=\"http://europa.eu/about-eu/facts-figures/administration/index_ro.htm#goto_2\">limbă oficială a UE</a>. Încercaţi să inseraţi toate detaliile de care este nevoie şi să vă asiguraţi că datele dumneavoastră de contact sunt corecte.</p>             <p>În mod normal, veţi primi un <strong>răspuns în termen de 3 zile lucrătoare</strong> (întrebările mai complexe ar putea necesita un termen mai lung).</p>             <p>                <iframe frameborder=\"0\" height=\"1020\" name=\"contacts_frame\" scrolling=\"no\"                        src=\"https://forms.communi-k.eu/livewebtools/WebForms/Standard/Standard.php?ro\"                        title=\"Mailbox\"                        width=\"90%\"/>             </p>             <p>                <strong>Declinarea responsabilităţii</strong>             </p>             <p>Acest serviciu este oferit de Europe Direct.  Informaţiile furnizate de Europe Direct nu au forţă juridică, indiferent de modalitatea prin care ne contactaţi.</p>"
      ],
      "sk": [
        "<p>Vyplňte uvedený formulár v ľubovoľnom <a href=\"http://europa.eu/about-eu/facts-figures/administration/index_sk.htm#goto_2\">úradnom jazyku EÚ</a>. Svoju otázku popíšte čo najpodrobnejšie a nezabudnite uviesť správne kontaktné údaje.</p>             <p>Obyčajne dostanete <strong>odpoveď do 3 pracovných dní</strong> (v prípade zložitejších otázok môže byť tento čas dlhší).</p>             <p>                <iframe frameborder=\"0\" height=\"1020\" name=\"contacts_frame\" scrolling=\"no\"                        src=\"https://forms.communi-k.eu/livewebtools/WebForms/Standard/Standard.php?sk\"                        title=\"Mailbox\"                        width=\"90%\"/>             </p>             <p>                <strong>Vyhlásenie o odmietnutí zodpovednosti</strong>             </p>             <p>Túto službu poskytuje Europe Direct.  Bez ohľadu na to, akým spôsobom nás kontaktujete, informácie, ktoré poskytuje služba Europe Direct, nie sú právne záväzné.</p>"
      ],
      "sl": [
        "<p>Spodaj vpišite svojo poizvedbo – v katerem koli <a href=\"http://europa.eu/about-eu/facts-figures/administration/index_sl.htm#goto_2\">uradnem jeziku EU</a>. Bodite čim bolj natančni in navedite pravilne kontaktne podatke.</p>             <p>Odgovor boste običajno prejeli <strong>v treh delovnih dneh</strong> (za zahtevnejše poizvedbe je morda potrebno več časa).</p>             <p>                <iframe frameborder=\"0\" height=\"1020\" name=\"contacts_frame\" scrolling=\"no\"                        src=\"https://forms.communi-k.eu/livewebtools/WebForms/Standard/Standard.php?sl\"                        title=\"Mailbox\"                        width=\"90%\"/>             </p>             <p>                <strong>Izjava o omejitvi odgovornosti</strong>             </p>             <p>To storitev zagotavlja Europe Direct.  Informacije, ki jih daje Europe Direct, niso pravno zavezujoče, ne glede na način, kako ste nas kontaktirali.</p>"
      ],
      "sv": [
        "<p>Skriv din fråga nedan – på vilket <a href=\"http://europa.eu/about-eu/facts-figures/administration/index_sv.htm#goto_2\">officiellt EU-språk</a> du vill. Förklara så noggrant du kan och se till att du anger rätt kontaktuppgifter.</p>             <p>Du får i regel <strong>svar inom tre arbetsdagar</strong>. För komplicerade frågor kan det dock ta längre tid.</p>             <p>                <iframe frameborder=\"0\" height=\"1020\" name=\"contacts_frame\" scrolling=\"no\"                        src=\"https://forms.communi-k.eu/livewebtools/WebForms/Standard/Standard.php?sv\"                        title=\"Mailbox\"                        width=\"90%\"/>             </p>             <p>                <strong>Ansvarsfriskrivning</strong>             </p>             <p>Det här är en tjänst från Europa direkt.  Informationen är inte rättsligt bindande, oavsett hur du har kontaktat oss.</p>"
      ]
    }
  }
}